{"displayFieldName":"fac_name","fieldAliases":{"OBJECTID":"OBJECTID","fac_no":"fac_no","fac_name":"fac_name","fac_addr":"fac_addr","utmX":"utmX","utmY":"utmY","type":"type"},"geometryType":"esriGeometryPoint","spatialReference":{"wkid":104137},"fields":[{"name":"OBJECTID","type":"esriFieldTypeOID","alias":"OBJECTID"},{"name":"fac_no","type":"esriFieldTypeString","alias":"fac_no","length":254},{"name":"fac_name","type":"esriFieldTypeString","alias":"fac_name","length":254},{"name":"fac_addr","type":"esriFieldTypeString","alias":"fac_addr","length":254},{"name":"utmX","type":"esriFieldTypeDouble","alias":"utmX"},{"name":"utmY","type":"esriFieldTypeDouble","alias":"utmY"},{"name":"type","type":"esriFieldTypeString","alias":"type","length":12}],"features":[{"attributes":{"OBJECTID":25201,"fac_no":"H42A1644","fac_name":"香港商瑞健股份有限公司台灣分公司桃園廠","fac_addr":"(330)桃園市桃園區中泰里國聖二街一三六號","utmX":279012,"utmY":2764027,"type":"事業機構"},"geometry":{"x":121.28738010519558,"y":24.983917776516765}},{"attributes":{"OBJECTID":25202,"fac_no":"F1312272","fac_name":"元福診所","fac_addr":"新北市土城區明德路二段六二號四樓","utmX":294684,"utmY":2764028,"type":"事業機構"},"geometry":{"x":121.44261706056824,"y":24.983546102967036}},{"attributes":{"OBJECTID":25203,"fac_no":"F05A0431","fac_name":"力鑫興業有限公司","fac_addr":"(231)新北市新店區中正路五一二號一樓","utmX":303906,"utmY":2764028,"type":"事業機構"},"geometry":{"x":121.53396265857887,"y":24.983246418481009}},{"attributes":{"OBJECTID":25204,"fac_no":"H4804684","fac_name":"明通企業股份有限公司二廠","fac_addr":"(333)桃園市龜山區福源里湖山街二\u25CB八號","utmX":285367,"utmY":2764029,"type":"事業機構"},"geometry":{"x":121.35032914520633,"y":24.983800973968496}},{"attributes":{"OBJECTID":25205,"fac_no":"H42B0534","fac_name":"豪豐營造股份有限公司","fac_addr":"(247)新北市蘆洲區光榮路九七巷六一號","utmX":276812,"utmY":2764031,"type":"事業機構"},"geometry":{"x":121.26558814309503,"y":24.983994372158836}},{"attributes":{"OBJECTID":25206,"fac_no":"F01B2038","fac_name":"成易精密工業股份有限公司","fac_addr":"(236)新北市土城區員仁里中央路二段三九四巷六號","utmX":293378,"utmY":2764035,"type":"事業機構"},"geometry":{"x":121.42968099720416,"y":24.983647209070568}},{"attributes":{"OBJECTID":25207,"fac_no":"H5205514","fac_name":"景碩科技股份有限公司清華一廠","fac_addr":"(327)桃園市新屋區清華里中華路八一\u25CB之一號","utmX":260692,"utmY":2764037,"type":"事業機構"},"geometry":{"x":121.10591077826408,"y":24.9842478252957}},{"attributes":{"OBJECTID":25208,"fac_no":"H42A7880","fac_name":"威慶營造有限公司","fac_addr":"(330)桃園市桃園區福昌街一八號七樓之一","utmX":281961,"utmY":2764037,"type":"事業機構"},"geometry":{"x":121.31659149719964,"y":24.983948789324113}},{"attributes":{"OBJECTID":25209,"fac_no":"F0508514","fac_name":"天宇工業股份有限公司第二廠","fac_addr":"(231)新北市新店區民權路一三\u25CB巷二號二樓","utmX":304002,"utmY":2764039,"type":"事業機構"},"geometry":{"x":121.53491397782132,"y":24.983342312070626}},{"attributes":{"OBJECTID":25210,"fac_no":"F0511717","fac_name":"定陽企業有限公司新店廠","fac_addr":"(231)新北市新店區寶橋路二三五巷一二三號四樓","utmX":305610,"utmY":2764039,"type":"事業機構"},"geometry":{"x":121.5508413653444,"y":24.98328421599043}},{"attributes":{"OBJECTID":25211,"fac_no":"H53A6346","fac_name":"裕鈞企業有限公司","fac_addr":"(328)桃園市觀音區崙坪里崙坪一之三一號及一之三二號","utmX":266312,"utmY":2764042,"type":"事業機構"},"geometry":{"x":121.16158021892639,"y":24.984242941216088}},{"attributes":{"OBJECTID":25212,"fac_no":"H48A1397","fac_name":"瑞怡造漆有限公司桃園廠","fac_addr":"(333)桃園市龜山區山頂里山鶯路一七一之一、一七一之五號","utmX":283220,"utmY":2764042,"type":"事業機構"},"geometry":{"x":121.32906255407752,"y":24.983966880506511}},{"attributes":{"OBJECTID":25213,"fac_no":"H43B0232","fac_name":"佶原營造有限公司","fac_addr":"(330)桃園市桃園區中興里孝二街三六號一樓","utmX":273686,"utmY":2764048,"type":"事業機構"},"geometry":{"x":121.23462384075003,"y":24.984199887810831}},{"attributes":{"OBJECTID":25214,"fac_no":"H4303093","fac_name":"台灣阿克蘇諾貝爾塗料股份有限公司得利製漆廠","fac_addr":"(320)桃園市中壢區東園路五二號及北園路三三號及三五號","utmX":274209,"utmY":2764050,"type":"事業機構"},"geometry":{"x":121.23980446473884,"y":24.98420968748874}},{"attributes":{"OBJECTID":25215,"fac_no":"H4202617","fac_name":"友聯車材製造股份有限公司","fac_addr":"(330)桃園市桃園區大林里興中街一號","utmX":282302,"utmY":2764051,"type":"事業機構"},"geometry":{"x":121.31996957781011,"y":24.984067961643248}},{"attributes":{"OBJECTID":25216,"fac_no":"H4809796","fac_name":"明通企業股份有限公司一廠","fac_addr":"(333)桃園市龜山區福源里湖山街一九五號","utmX":285337,"utmY":2764052,"type":"事業機構"},"geometry":{"x":121.35003257132078,"y":24.984009322498881}},{"attributes":{"OBJECTID":25217,"fac_no":"H43B6200","fac_name":"華星光通科技股份有限公司合江廠","fac_addr":"(320)桃園市中壢區文化里合江路六號","utmX":274746,"utmY":2764055,"type":"事業機構"},"geometry":{"x":121.24512381889916,"y":24.984246163453435}},{"attributes":{"OBJECTID":25218,"fac_no":"F0508550","fac_name":"五義企業股份有限公司","fac_addr":"(231)新北市新店區民權路四二巷五九弄三號三樓","utmX":304357,"utmY":2764061,"type":"事業機構"},"geometry":{"x":121.53843115457703,"y":24.983528248780377}},{"attributes":{"OBJECTID":25219,"fac_no":"A40A7592","fac_name":"萬堡營造股份有限公司","fac_addr":"(100)台北市中正區仁愛路二段二號七樓","utmX":307230,"utmY":2764062,"type":"事業機構"},"geometry":{"x":121.56688851507504,"y":24.98343160600648}},{"attributes":{"OBJECTID":25220,"fac_no":"F0506261","fac_name":"研揚科技股份有限公司","fac_addr":"(231)新北市新店區寶橋路二三五巷一三一號五樓、五樓之一、之二、之三、之四、一三三號五樓．五樓之一．之二．之三．一三五號五樓．五樓之一、之二、之三、一三七號五樓、五樓之ㄧ、之二、之三、之四","utmX":304986,"utmY":2764064,"type":"事業機構"},"geometry":{"x":121.54466158824277,"y":24.983532662922762}},{"attributes":{"OBJECTID":25221,"fac_no":"F0512223","fac_name":"四零四科技股份有限公司新店一廠","fac_addr":"(231)新北市新店區寶橋路二三五巷一三五號四樓","utmX":304986,"utmY":2764064,"type":"事業機構"},"geometry":{"x":121.54466158824277,"y":24.983532662922762}},{"attributes":{"OBJECTID":25222,"fac_no":"H48A9470","fac_name":"欣興電子股份有限公司山鶯文華廠","fac_addr":"(330)桃園市桃園區龜山工業區興邦路三八號","utmX":283188,"utmY":2764066,"type":"事業機構"},"geometry":{"x":121.32874615654285,"y":24.984184259047456}},{"attributes":{"OBJECTID":25223,"fac_no":"F0711511","fac_name":"禾名化工股份有限公司樹林廠","fac_addr":"(238)新北市樹林區東順街八四號","utmX":290948,"utmY":2764066,"type":"事業機構"},"geometry":{"x":121.40561202790126,"y":24.983994625760378}},{"attributes":{"OBJECTID":25224,"fac_no":"F0714441","fac_name":"一友實業有限公司","fac_addr":"(238)新北市樹林區三龍街三五號","utmX":290948,"utmY":2764066,"type":"事業機構"},"geometry":{"x":121.40561202790126,"y":24.983994625760378}},{"attributes":{"OBJECTID":25225,"fac_no":"F0721062","fac_name":"台盟電子股份有限公司樹林一廠","fac_addr":"(238)新北市樹林區三龍街二\u25CB二號","utmX":290948,"utmY":2764066,"type":"事業機構"},"geometry":{"x":121.40561202790126,"y":24.983994625760378}},{"attributes":{"OBJECTID":25226,"fac_no":"F0725686","fac_name":"昱盟企業有限公司","fac_addr":"(238)新北市樹林區三龍街二\u25CB\u25CB號","utmX":290948,"utmY":2764066,"type":"事業機構"},"geometry":{"x":121.40561202790126,"y":24.983994625760378}},{"attributes":{"OBJECTID":25227,"fac_no":"F07A2051","fac_name":"家祥診所","fac_addr":"(238)新北市樹林區保安街一段五四號一、二樓","utmX":290948,"utmY":2764066,"type":"事業機構"},"geometry":{"x":121.40561202790126,"y":24.983994625760378}},{"attributes":{"OBJECTID":25228,"fac_no":"F07A2091","fac_name":"揚禾數位有限公司","fac_addr":"(238)新北市樹林區保安街一段六七號","utmX":290948,"utmY":2764066,"type":"事業機構"},"geometry":{"x":121.40561202790126,"y":24.983994625760378}},{"attributes":{"OBJECTID":25229,"fac_no":"F07A2487","fac_name":"安心食品服務股份有限公司學成分公司","fac_addr":"(238)新北市樹林區學成路七一二、七一六、七二二號","utmX":290948,"utmY":2764066,"type":"事業機構"},"geometry":{"x":121.40561202790126,"y":24.983994625760378}},{"attributes":{"OBJECTID":25230,"fac_no":"F07A2615","fac_name":"宏裕營造有限公司","fac_addr":"(220)新北市板橋區永豐街二四號二樓","utmX":290948,"utmY":2764066,"type":"事業機構"},"geometry":{"x":121.40561202790126,"y":24.983994625760378}},{"attributes":{"OBJECTID":25231,"fac_no":"F07A2625","fac_name":"宏裕營造有限公司","fac_addr":"(220)新北市板橋區永豐街二四號二樓","utmX":290948,"utmY":2764066,"type":"事業機構"},"geometry":{"x":121.40561202790126,"y":24.983994625760378}},{"attributes":{"OBJECTID":25232,"fac_no":"F07A2665","fac_name":"松禾診所","fac_addr":"(238)新北市樹林區鎮前街五八號二樓","utmX":290948,"utmY":2764066,"type":"事業機構"},"geometry":{"x":121.40561202790126,"y":24.983994625760378}},{"attributes":{"OBJECTID":25233,"fac_no":"F07A7041","fac_name":"紹華營造股份有限公司","fac_addr":"(242)新北市新莊區中華路二段一三號一\u25CB樓","utmX":290948,"utmY":2764066,"type":"事業機構"},"geometry":{"x":121.40561202790126,"y":24.983994625760378}},{"attributes":{"OBJECTID":25234,"fac_no":"H4213316","fac_name":"陽宇電子股份有限公司","fac_addr":"(330)桃園市桃園區龍山里龍壽街二七三巷八號一樓","utmX":276198,"utmY":2764068,"type":"事業機構"},"geometry":{"x":121.25950687401182,"y":24.984339148372616}},{"attributes":{"OBJECTID":25235,"fac_no":"F05A5342","fac_name":"漢志電子股份有限公司第一廠","fac_addr":"(231)新北市新店區中正路五\u25CB一號四樓","utmX":303867,"utmY":2764069,"type":"事業機構"},"geometry":{"x":121.53357795701223,"y":24.983617952275612}},{"attributes":{"OBJECTID":25236,"fac_no":"F0705719","fac_name":"啟鈦工業有限公司","fac_addr":"新北市樹林區中山路二段214巷1號","utmX":290517,"utmY":2764072,"type":"事業機構"},"geometry":{"x":121.40134299929093,"y":24.984060368460646}},{"attributes":{"OBJECTID":25237,"fac_no":"F0501186","fac_name":"鑫合實業有限公司","fac_addr":"新北市新店區民權路42巷45-1號","utmX":304404,"utmY":2764072,"type":"事業機構"},"geometry":{"x":121.53889712786304,"y":24.983625871881177}},{"attributes":{"OBJECTID":25238,"fac_no":"H42A4094","fac_name":"德文工程有限公司","fac_addr":"(103)台北市大同區重慶北路三段九六號七樓","utmX":280257,"utmY":2764073,"type":"事業機構"},"geometry":{"x":121.29971340372694,"y":24.984308754206211}},{"attributes":{"OBJECTID":25239,"fac_no":"H4813450","fac_name":"三協彫刻廠股份有限公司","fac_addr":"(333)桃園市龜山區福源里湖山街一八\u25CB巷一弄三號","utmX":285506,"utmY":2764076,"type":"事業機構"},"geometry":{"x":121.35170720154377,"y":24.984222053599304}},{"attributes":{"OBJECTID":25240,"fac_no":"H43C5744","fac_name":"植煇營造有限公司","fac_addr":"(220)新北市板橋區挹秀里民權路七一號四樓","utmX":275345,"utmY":2764079,"type":"事業機構"},"geometry":{"x":121.25105766505017,"y":24.984452952557987}},{"attributes":{"OBJECTID":25241,"fac_no":"H4202715","fac_name":"杏隆實業股份有限公司桃園廠","fac_addr":"(330)桃園市桃園區大林里興隆路九號","utmX":282450,"utmY":2764082,"type":"事業機構"},"geometry":{"x":121.32143631097516,"y":24.984344678751725}},{"attributes":{"OBJECTID":25242,"fac_no":"H5308298","fac_name":"台灣亞旭科技股份有限公司","fac_addr":"新北市新店區民權路100號11樓","utmX":257750,"utmY":2764085,"type":"事業機構"},"geometry":{"x":121.07676876832954,"y":24.984699072904824}},{"attributes":{"OBJECTID":25243,"fac_no":"F01B2325","fac_name":"柏盈實業股份有限公司","fac_addr":"(220)新北市板橋區金門街三六九巷六一號","utmX":293356,"utmY":2764085,"type":"事業機構"},"geometry":{"x":121.42946464888641,"y":24.984099245409013}},{"attributes":{"OBJECTID":25244,"fac_no":"H43C4469","fac_name":"福容大飯店 中壢","fac_addr":"NULL","utmX":268856,"utmY":2764087,"type":"事業機構"},"geometry":{"x":121.18678059179574,"y":24.984619725744956}},{"attributes":{"OBJECTID":25245,"fac_no":"F07A6320","fac_name":"億東營造股份有限公司","fac_addr":"(231)新北市新店區民族路一\u25CB二號一樓","utmX":291486,"utmY":2764089,"type":"事業機構"},"geometry":{"x":121.4109417908719,"y":24.984187654925194}},{"attributes":{"OBJECTID":25246,"fac_no":"F0514932","fac_name":"天宇工業股份有限公司","fac_addr":"(231)新北市新店區民權路一三\u25CB巷八號五樓","utmX":303999,"utmY":2764089,"type":"事業機構"},"geometry":{"x":121.53488621531808,"y":24.983793819238127}},{"attributes":{"OBJECTID":25247,"fac_no":"H43B4729","fac_name":"萬代福營造有限公司","fac_addr":"(248)新北市五股區成泰路一段二號八樓","utmX":271600,"utmY":2764092,"type":"事業機構"},"geometry":{"x":121.21396158339707,"y":24.984628273905884}},{"attributes":{"OBJECTID":25248,"fac_no":"F0510327","fac_name":"宣佑科技電子股份有限公司新店廠","fac_addr":"(231)新北市新店區中正路五\u25CB一之一七號四樓","utmX":303837,"utmY":2764093,"type":"事業機構"},"geometry":{"x":121.53328173761214,"y":24.983835689537159}},{"attributes":{"OBJECTID":25249,"fac_no":"H42A8501","fac_name":"中元營造有限公司","fac_addr":"(260)宜蘭縣宜蘭市中山路三段九五號","utmX":276814,"utmY":2764097,"type":"事業機構"},"geometry":{"x":121.26560923414465,"y":24.984590204890612}},{"attributes":{"OBJECTID":25250,"fac_no":"F07A7061","fac_name":"永騰營造有限公司","fac_addr":"(220)新北市板橋區溪北路一七\u25CB號七樓","utmX":291686,"utmY":2764097,"type":"事業機構"},"geometry":{"x":121.4129231023034,"y":24.984254397088236}},{"attributes":{"OBJECTID":25251,"fac_no":"H4304821","fac_name":"欣興電子股份有限公司合江廠","fac_addr":"(320)桃園市中壢區合江路一二號","utmX":274627,"utmY":2764098,"type":"事業機構"},"geometry":{"x":121.24394582768339,"y":24.984636317903465}},{"attributes":{"OBJECTID":25252,"fac_no":"F04A5288","fac_name":"華夏技術學院","fac_addr":"(235)新北市中和區工專路一一一號","utmX":300312,"utmY":2764099,"type":"事業機構"},"geometry":{"x":121.49836619021096,"y":24.984010870167694}},{"attributes":{"OBJECTID":25253,"fac_no":"F04B7211","fac_name":"華夏學校財團法人華夏科技大學","fac_addr":"(235)新北市中和區工專路一一一號","utmX":300312,"utmY":2764099,"type":"事業機構"},"geometry":{"x":121.49836619021096,"y":24.984010870167694}},{"attributes":{"OBJECTID":25254,"fac_no":"H48A0111","fac_name":"陽美企業有限公司","fac_addr":"(333)桃園市龜山區南上里民生北路一段一六六巷五號","utmX":281890,"utmY":2764102,"type":"事業機構"},"geometry":{"x":121.31588971044104,"y":24.984537120819599}},{"attributes":{"OBJECTID":25255,"fac_no":"H4889856","fac_name":"晨光興業有限公司","fac_addr":"(333)桃園市龜山區山頂里山鶯路三二六之二號","utmX":283112,"utmY":2764107,"type":"事業機構"},"geometry":{"x":121.32799432470948,"y":24.98455607836248}},{"attributes":{"OBJECTID":25256,"fac_no":"F13A4190","fac_name":"合興預拌混凝土股份有限公司土城廠","fac_addr":"(236)新北市土城區中華路一段一六二號","utmX":294650,"utmY":2764107,"type":"事業機構"},"geometry":{"x":121.44228283303828,"y":24.984260326564577}},{"attributes":{"OBJECTID":25257,"fac_no":"F05A3841","fac_name":"全凱數位資訊有限公司","fac_addr":"(231)新北市新店區中正路五\u25CB一之一三號三樓","utmX":303857,"utmY":2764112,"type":"事業機構"},"geometry":{"x":121.53348058072727,"y":24.98400651174823}},{"attributes":{"OBJECTID":25258,"fac_no":"H4301106","fac_name":"台灣資生堂股份有限公司","fac_addr":"(320)桃園市中壢區忠福里西園路一四八號","utmX":273804,"utmY":2764113,"type":"事業機構"},"geometry":{"x":121.23579381194098,"y":24.984784881722241}},{"attributes":{"OBJECTID":25259,"fac_no":"H42B4526","fac_name":"祥禎食品有限公司","fac_addr":"(330)桃園市桃園區雲林里桃鶯路二一七號","utmX":282157,"utmY":2764114,"type":"事業機構"},"geometry":{"x":121.31853475372165,"y":24.98463982300947}},{"attributes":{"OBJECTID":25260,"fac_no":"H4249576","fac_name":"怡和餐飲股份有限公司桃園中山分公司","fac_addr":"(330)桃園市桃園區中路里中山路八二四至八三六號","utmX":278066,"utmY":2764116,"type":"事業機構"},"geometry":{"x":121.27801134071133,"y":24.984739093226569}},{"attributes":{"OBJECTID":25261,"fac_no":"H48A6436","fac_name":"明基三豐醫療器材股份有限公司龜山廠","fac_addr":"(333)桃園市龜山區山頂里山鶯路一五九號三樓","utmX":283121,"utmY":2764116,"type":"事業機構"},"geometry":{"x":121.32808368960022,"y":24.984637136142194}},{"attributes":{"OBJECTID":25262,"fac_no":"H43B8424","fac_name":"欣興電子股份有限公司合江二廠","fac_addr":"(320)桃園市中壢區文化里合圳南路二號","utmX":274806,"utmY":2764120,"type":"事業機構"},"geometry":{"x":121.24571931650028,"y":24.984832024092057}},{"attributes":{"OBJECTID":25263,"fac_no":"F13A5613","fac_name":"怡和餐飲股份有限公司土城金城分公司","fac_addr":"(236)新北市土城區金城路二段二六九號、二七一號","utmX":296332,"utmY":2764123,"type":"事業機構"},"geometry":{"x":121.45894409142774,"y":24.984354332788424}},{"attributes":{"OBJECTID":25264,"fac_no":"F05A2645","fac_name":"精聯電子股份有限公司","fac_addr":"(231)新北市新店區寶橋路二三五巷一三\u25CB至一三八號五樓、一三\u25CB之一之二之三之五號五樓、一三二號五樓之一之二","utmX":305760,"utmY":2764123,"type":"事業機構"},"geometry":{"x":121.55233051429643,"y":24.984037060089033}},{"attributes":{"OBJECTID":25265,"fac_no":"H5205578","fac_name":"鈺新金屬廠有限公司壓鑄廠","fac_addr":"(327)桃園市新屋區永安里下庄子二三八之八號","utmX":252695,"utmY":2764126,"type":"事業機構"},"geometry":{"x":121.02669580831628,"y":24.985086642157039}},{"attributes":{"OBJECTID":25266,"fac_no":"H5205676","fac_name":"茂嘉實業有限公司新屋廠","fac_addr":"(327)桃園市新屋區永安里下庄子二三八之三號","utmX":252695,"utmY":2764126,"type":"事業機構"},"geometry":{"x":121.02669580831628,"y":24.985086642157039}},{"attributes":{"OBJECTID":25267,"fac_no":"F13A4487","fac_name":"富利食品股份有限公司裕民外送分公司","fac_addr":"(236)新北市土城區裕民路一八九號一樓","utmX":295799,"utmY":2764126,"type":"事業機構"},"geometry":{"x":121.45366466222582,"y":24.984397603884133}},{"attributes":{"OBJECTID":25268,"fac_no":"F05A8910","fac_name":"建國工程股份有限公司","fac_addr":"(106)台北市大安區敦化南路二段六七號二\u25CB樓","utmX":303150,"utmY":2764126,"type":"事業機構"},"geometry":{"x":121.52647816426278,"y":24.984157841274421}},{"attributes":{"OBJECTID":25269,"fac_no":"H48A4549","fac_name":"欣點科技股份有限公司","fac_addr":"(333)桃園市龜山區山頂里山鶯路一六九之一號","utmX":283246,"utmY":2764128,"type":"事業機構"},"geometry":{"x":121.32932216325347,"y":24.984742740535474}},{"attributes":{"OBJECTID":25270,"fac_no":"F13A5970","fac_name":"羿富營造有限公司","fac_addr":"(248)新北市五股區五股里成泰路二段一一巷二二號四樓","utmX":296590,"utmY":2764129,"type":"事業機構"},"geometry":{"x":121.4614998611537,"y":24.984400598935469}},{"attributes":{"OBJECTID":25271,"fac_no":"F13A5980","fac_name":"羿富營造有限公司","fac_addr":"(248)新北市五股區五股里成泰路二段一一巷二二號四樓","utmX":296590,"utmY":2764129,"type":"事業機構"},"geometry":{"x":121.4614998611537,"y":24.984400598935469}},{"attributes":{"OBJECTID":25272,"fac_no":"H43A8180","fac_name":"長鴻電子股份有限公司中壢北園廠","fac_addr":"(320)桃園市中壢區復興里北園路三\u25CB號","utmX":274485,"utmY":2764130,"type":"事業機構"},"geometry":{"x":121.24253980564784,"y":24.984927523004654}},{"attributes":{"OBJECTID":25273,"fac_no":"H42B5069","fac_name":"富榮營造有限公司","fac_addr":"(338)桃園市蘆竹區大竹村大興十四街一二八號一樓","utmX":280302,"utmY":2764133,"type":"事業機構"},"geometry":{"x":121.30016046550909,"y":24.984849552525375}},{"attributes":{"OBJECTID":25274,"fac_no":"F05B1000","fac_name":"昶永有限公司","fac_addr":"(231)新北市新店區中正路五\u25CB三之三號五樓","utmX":303852,"utmY":2764136,"type":"事業機構"},"geometry":{"x":121.53343198974241,"y":24.9842233614789}},{"attributes":{"OBJECTID":25275,"fac_no":"H49A6728","fac_name":"坤旺營造有限公司","fac_addr":"(325)桃園市龍潭區龍星里龍青路一二巷六號","utmX":277195,"utmY":2764138,"type":"事業機構"},"geometry":{"x":121.26938404835771,"y":24.984953582149373}},{"attributes":{"OBJECTID":25276,"fac_no":"H49A7073","fac_name":"坤弘營造有限公司","fac_addr":"(325)桃園市龍潭區龍星里龍青路一二巷六號","utmX":277195,"utmY":2764138,"type":"事業機構"},"geometry":{"x":121.26938404835771,"y":24.984953582149373}},{"attributes":{"OBJECTID":25277,"fac_no":"F05B2107","fac_name":"磁量生技股份有限公司","fac_addr":"(231)新北市新店區復興里中正路五三八巷七、一二號三樓","utmX":303953,"utmY":2764139,"type":"事業機構"},"geometry":{"x":121.53443252990773,"y":24.984246856436631}},{"attributes":{"OBJECTID":25278,"fac_no":"H4213129","fac_name":"家穎實業股份有限公司","fac_addr":"(330)桃園市桃園區龍岡里龍壽街二七三巷二七號","utmX":276785,"utmY":2764140,"type":"事業機構"},"geometry":{"x":121.26532280677033,"y":24.98497893433785}},{"attributes":{"OBJECTID":25279,"fac_no":"H42B3112","fac_name":"恩興營造有限公司","fac_addr":"(330)桃園市桃園區中寧里大興西路二段九六巷二一之一號","utmX":279671,"utmY":2764140,"type":"事業機構"},"geometry":{"x":121.29391022740083,"y":24.984925225070114}},{"attributes":{"OBJECTID":25280,"fac_no":"H4249352","fac_name":"凱崴電子股份有限公司桃園廠","fac_addr":"(330)桃園市桃園區大林里興邦路三二號一、二、三樓","utmX":281809,"utmY":2764141,"type":"事業機構"},"geometry":{"x":121.31508826343428,"y":24.984890923913323}},{"attributes":{"OBJECTID":25281,"fac_no":"F01B4371","fac_name":"台灣麥當勞餐廳股份有限公司板橋篤行門市部","fac_addr":"(220)新北市板橋區篤行路三段九九號地下一層及一樓","utmX":293032,"utmY":2764142,"type":"事業機構"},"geometry":{"x":121.42625709797738,"y":24.984623076153433}},{"attributes":{"OBJECTID":25282,"fac_no":"H42B3043","fac_name":"香港商瑞鴻模具有限公司台灣分公司","fac_addr":"(330)桃園市桃園區中泰里中山路九三九之一號","utmX":278784,"utmY":2764143,"type":"事業機構"},"geometry":{"x":121.28512407481212,"y":24.984969401725298}},{"attributes":{"OBJECTID":25283,"fac_no":"F0514129","fac_name":"新力姿股份有限公司","fac_addr":"(231)新北市新店區建國路二三六號一樓","utmX":303451,"utmY":2764143,"type":"事業機構"},"geometry":{"x":121.52946028164799,"y":24.984300740886273}},{"attributes":{"OBJECTID":25284,"fac_no":"H43C1990","fac_name":"台灣中外電氣工業股份有限公司","fac_addr":"(320)桃園市中壢區內定里松江北路二號一樓","utmX":275196,"utmY":2764144,"type":"事業機構"},"geometry":{"x":121.24958292499646,"y":24.985042275397671}},{"attributes":{"OBJECTID":25285,"fac_no":"H42A8799","fac_name":"順泰營造有限公司","fac_addr":"(320)桃園市中壢區幸福里延平路一一八號三樓","utmX":281062,"utmY":2764144,"type":"事業機構"},"geometry":{"x":121.30768890853669,"y":24.984933490188734}},{"attributes":{"OBJECTID":25286,"fac_no":"H42B4457","fac_name":"品承營造股份有限公司","fac_addr":"(104)台北市中山區中山北路三段四九號七樓之三","utmX":282424,"utmY":2764144,"type":"事業機構"},"geometry":{"x":121.32118022299964,"y":24.984904986800686}},{"attributes":{"OBJECTID":25287,"fac_no":"H4806455","fac_name":"台灣華歌爾股份有限公司二廠","fac_addr":"(333)桃園市龜山區山頂里興邦路二七、二九號","utmX":281836,"utmY":2764145,"type":"事業機構"},"geometry":{"x":121.31535580443096,"y":24.984926470508391}},{"attributes":{"OBJECTID":25288,"fac_no":"H4210404","fac_name":"台灣美琪電子工業股份有限公司二廠","fac_addr":"(330)桃園市桃園區南豐街八八號四至六樓之一、二、三、四","utmX":280908,"utmY":2764146,"type":"事業機構"},"geometry":{"x":121.30616350231162,"y":24.984954692625916}},{"attributes":{"OBJECTID":25289,"fac_no":"H4210708","fac_name":"遠百企業股份有限公司桃園分公司","fac_addr":"(330)桃園市桃園區中山路九三九號","utmX":278825,"utmY":2764148,"type":"事業機構"},"geometry":{"x":121.28553030651968,"y":24.985013764561767}},{"attributes":{"OBJECTID":25290,"fac_no":"H4221050","fac_name":"苙騰精密股份有限公司","fac_addr":"桃園市桃園區玉山里玉山街226巷4號","utmX":280267,"utmY":2764148,"type":"事業機構"},"geometry":{"x":121.29981410053075,"y":24.984985675487557}},{"attributes":{"OBJECTID":25291,"fac_no":"H4301071","fac_name":"三宜油化股份有限公司","fac_addr":"(320)桃園市中壢區復興里合圳南路五號","utmX":274779,"utmY":2764149,"type":"事業機構"},"geometry":{"x":121.24545238593585,"y":24.985094286627938}},{"attributes":{"OBJECTID":25292,"fac_no":"H42B2233","fac_name":"鑫美攝影社","fac_addr":"(330)桃園市桃園區雲林里桃鶯路二\u25CB一號一樓","utmX":282146,"utmY":2764152,"type":"事業機構"},"geometry":{"x":121.31842667691376,"y":24.984983130093482}},{"attributes":{"OBJECTID":25293,"fac_no":"H43B3652","fac_name":"汯寬科技股份有限公司","fac_addr":"(320)桃園市中壢區文化里合圳南路二號","utmX":274800,"utmY":2764155,"type":"事業機構"},"geometry":{"x":121.24566051095471,"y":24.985148113319678}},{"attributes":{"OBJECTID":25294,"fac_no":"F0507704","fac_name":"長晟電機有限公司","fac_addr":"新北市新店區中正路５３８巷８號","utmX":303950,"utmY":2764156,"type":"事業機構"},"geometry":{"x":121.53440347774921,"y":24.984400439262561}},{"attributes":{"OBJECTID":25295,"fac_no":"H48A1090","fac_name":"尚佳纖維股份有限公司","fac_addr":"(333)桃園市龜山區福源里湖山街一八\u25CB巷一弄一\u25CB號","utmX":285571,"utmY":2764157,"type":"事業機構"},"geometry":{"x":121.35235313815284,"y":24.984951817330206}},{"attributes":{"OBJECTID":25296,"fac_no":"F13A5851","fac_name":"東伸紙器有限公司","fac_addr":"(236)新北市土城區裕民路一八五巷三號","utmX":295806,"utmY":2764160,"type":"事業機構"},"geometry":{"x":121.4537351259241,"y":24.984704348493992}},{"attributes":{"OBJECTID":25297,"fac_no":"H4306281","fac_name":"富茂電線電纜股份有限公司","fac_addr":"(320)桃園市中壢區松柏路八號","utmX":275005,"utmY":2764163,"type":"事業機構"},"geometry":{"x":121.24769130223329,"y":24.98521697415757}},{"attributes":{"OBJECTID":25298,"fac_no":"H42B2520","fac_name":"侑甫營造工程有限公司","fac_addr":"(334)桃園市八德區興仁里中興街四二號一樓","utmX":282135,"utmY":2764164,"type":"事業機構"},"geometry":{"x":121.31831799514647,"y":24.985091702311188}},{"attributes":{"OBJECTID":25299,"fac_no":"F0713819","fac_name":"巨鎧實業股份有限公司","fac_addr":"(238)新北市樹林區和平里鎮前街二六九巷二九弄四號","utmX":292355,"utmY":2764164,"type":"事業機構"},"geometry":{"x":121.41955183442316,"y":24.984840750821991}},{"attributes":{"OBJECTID":25300,"fac_no":"H42B1562","fac_name":"同家營造有限公司","fac_addr":"(324)桃園市平鎮區東安里平等路四二號","utmX":279387,"utmY":2764165,"type":"事業機構"},"geometry":{"x":121.29109758600221,"y":24.98515646107046}},{"attributes":{"OBJECTID":25301,"fac_no":"H48A4054","fac_name":"銳捷科技股份有限公司二廠","fac_addr":"(333)桃園市龜山區山頂里山鶯路文華巷五號","utmX":283389,"utmY":2764166,"type":"事業機構"},"geometry":{"x":121.33073956576399,"y":24.985082672974094}},{"attributes":{"OBJECTID":25302,"fac_no":"F13A4318","fac_name":"安心食品服務股份有限公司土城裕民門市部","fac_addr":"(236)新北市土城區裕民路一七九號一、二樓","utmX":295782,"utmY":2764171,"type":"事業機構"},"geometry":{"x":121.45349776208162,"y":24.984804382356998}},{"attributes":{"OBJECTID":25303,"fac_no":"F07A4512","fac_name":"金奕科技有限公司","fac_addr":"(238)新北市樹林區鎮前街二六九巷二九弄一六號(一、二、三樓)","utmX":292344,"utmY":2764172,"type":"事業機構"},"geometry":{"x":121.41944312011982,"y":24.984913283206254}},{"attributes":{"OBJECTID":25304,"fac_no":"F0500643","fac_name":"大勵彩色印刷股份有限公司","fac_addr":"(231)新北市新店區中正路五三八巷三號一樓","utmX":303937,"utmY":2764173,"type":"事業機構"},"geometry":{"x":121.53427537347081,"y":24.984554377699517}},{"attributes":{"OBJECTID":25305,"fac_no":"F08A2571","fac_name":"安住營造股份有限公司","fac_addr":"(100)台北市中正區忠孝東路二段三九巷二弄二號一樓","utmX":288175,"utmY":2764176,"type":"事業機構"},"geometry":{"x":121.37814749345286,"y":24.985060050874448}},{"attributes":{"OBJECTID":25306,"fac_no":"F08A2660","fac_name":"宏裕營造有限公司","fac_addr":"(220)新北市板橋區永豐街二四號二樓","utmX":288175,"utmY":2764176,"type":"事業機構"},"geometry":{"x":121.37814749345286,"y":24.985060050874448}},{"attributes":{"OBJECTID":25307,"fac_no":"F08A2769","fac_name":"合昱營造股份有限公司","fac_addr":"(330)桃園市桃園區文中路七四七號一一樓","utmX":288175,"utmY":2764176,"type":"事業機構"},"geometry":{"x":121.37814749345286,"y":24.985060050874448}},{"attributes":{"OBJECTID":25308,"fac_no":"F08A2779","fac_name":"永裕泰工程股份有限公司","fac_addr":"(220)新北市板橋區重慶路一\u25CB號九樓","utmX":288175,"utmY":2764176,"type":"事業機構"},"geometry":{"x":121.37814749345286,"y":24.985060050874448}},{"attributes":{"OBJECTID":25309,"fac_no":"F08A2789","fac_name":"洛城營造有限公司","fac_addr":"(248)新北市五股區成泰路一段二號一\u25CB樓","utmX":288175,"utmY":2764176,"type":"事業機構"},"geometry":{"x":121.37814749345286,"y":24.985060050874448}},{"attributes":{"OBJECTID":25310,"fac_no":"F08A2818","fac_name":"唯秀營造有限公司","fac_addr":"(239)新北市鶯歌區鶯桃路五八七號(一樓)","utmX":288175,"utmY":2764176,"type":"事業機構"},"geometry":{"x":121.37814749345286,"y":24.985060050874448}},{"attributes":{"OBJECTID":25311,"fac_no":"F08A2868","fac_name":"中元營造有限公司","fac_addr":"(260)宜蘭縣宜蘭市中山路三段九五號","utmX":288175,"utmY":2764176,"type":"事業機構"},"geometry":{"x":121.37814749345286,"y":24.985060050874448}},{"attributes":{"OBJECTID":25312,"fac_no":"F08A3272","fac_name":"六大營造股份有限公司","fac_addr":"(330)桃園市桃園區中正路一\u25CB七一號二\u25CB樓之一","utmX":288175,"utmY":2764176,"type":"事業機構"},"geometry":{"x":121.37814749345286,"y":24.985060050874448}},{"attributes":{"OBJECTID":25313,"fac_no":"F08A3341","fac_name":"萬代福營造有限公司","fac_addr":"(248)新北市五股區成泰路一段二號八樓","utmX":288175,"utmY":2764176,"type":"事業機構"},"geometry":{"x":121.37814749345286,"y":24.985060050874448}},{"attributes":{"OBJECTID":25314,"fac_no":"F08A3391","fac_name":"京富祥營造股份有限公司","fac_addr":"(105)台北市松山區八德路三段三\u25CB號一二樓","utmX":288175,"utmY":2764176,"type":"事業機構"},"geometry":{"x":121.37814749345286,"y":24.985060050874448}},{"attributes":{"OBJECTID":25315,"fac_no":"F08A3400","fac_name":"華德開發營造有限公司","fac_addr":"(334)桃園市八德區金和路六五號八樓","utmX":288175,"utmY":2764176,"type":"事業機構"},"geometry":{"x":121.37814749345286,"y":24.985060050874448}},{"attributes":{"OBJECTID":25316,"fac_no":"F08A3519","fac_name":"陳瑞祥","fac_addr":"(239)新北市鶯歌區中正二路一七三之一號","utmX":288175,"utmY":2764176,"type":"事業機構"},"geometry":{"x":121.37814749345286,"y":24.985060050874448}},{"attributes":{"OBJECTID":25317,"fac_no":"F08A3559","fac_name":"達昱營造有限公司","fac_addr":"(202)基隆市中正區新豐街二五一巷五弄一六號一樓","utmX":288175,"utmY":2764176,"type":"事業機構"},"geometry":{"x":121.37814749345286,"y":24.985060050874448}},{"attributes":{"OBJECTID":25318,"fac_no":"F08A3579","fac_name":"立源營造股份有限公司","fac_addr":"(103)台北市大同區承德路三段二三\u25CB號七樓","utmX":288175,"utmY":2764176,"type":"事業機構"},"geometry":{"x":121.37814749345286,"y":24.985060050874448}},{"attributes":{"OBJECTID":25319,"fac_no":"F08A3628","fac_name":"群越營造股份有限公司","fac_addr":"(330)桃園市桃園區新埔六街一\u25CB一號二一樓","utmX":288175,"utmY":2764176,"type":"事業機構"},"geometry":{"x":121.37814749345286,"y":24.985060050874448}},{"attributes":{"OBJECTID":25320,"fac_no":"F08A2690","fac_name":"利榮營造有限公司","fac_addr":"(337)桃園市大園區永園路二段一八三巷一三九號","utmX":288176,"utmY":2764176,"type":"事業機構"},"geometry":{"x":121.3781573989145,"y":24.985060025705948}},{"attributes":{"OBJECTID":25321,"fac_no":"F08A3173","fac_name":"巨達營造有限公司","fac_addr":"(330)桃園市桃園區復興路四五六之九號","utmX":288176,"utmY":2764176,"type":"事業機構"},"geometry":{"x":121.3781573989145,"y":24.985060025705948}},{"attributes":{"OBJECTID":25322,"fac_no":"H5201374","fac_name":"鼎鐘實業行","fac_addr":"(327)桃園市新屋區頭洲里犁頭洲三六之六號","utmX":252291,"utmY":2764177,"type":"事業機構"},"geometry":{"x":121.02269399827692,"y":24.985547754568774}},{"attributes":{"OBJECTID":25323,"fac_no":"F0505273","fac_name":"今一彩色印刷股份有限公司","fac_addr":"(231)新北市新店區中正路五\u25CB一之一六號","utmX":303800,"utmY":2764177,"type":"事業機構"},"geometry":{"x":121.53291851583474,"y":24.984595355073989}},{"attributes":{"OBJECTID":25324,"fac_no":"F0500929","fac_name":"酈傳股份有限公司","fac_addr":"新北市新店區民權路130巷12號5樓","utmX":304015,"utmY":2764177,"type":"事業機構"},"geometry":{"x":121.53504813570173,"y":24.984587714149843}},{"attributes":{"OBJECTID":25325,"fac_no":"H5300363","fac_name":"銓盟企業股份有限公司","fac_addr":"(328)桃園市觀音區富源里新富路一五六\u25CB號","utmX":263608,"utmY":2764178,"type":"事業機構"},"geometry":{"x":121.13479686759005,"y":24.985497468894515}},{"attributes":{"OBJECTID":25326,"fac_no":"H43B1101","fac_name":"台灣旭硝子電子股份有限公司","fac_addr":"(320)桃園市中壢區內定里松江北路二號一樓","utmX":275102,"utmY":2764178,"type":"事業機構"},"geometry":{"x":121.24865241756042,"y":24.985350796677547}},{"attributes":{"OBJECTID":25327,"fac_no":"H42B3182","fac_name":"洲義營造有限公司","fac_addr":"(970)花蓮縣花蓮市國富里國富十街一一六號","utmX":280575,"utmY":2764181,"type":"事業機構"},"geometry":{"x":121.30286573501188,"y":24.98527743125306}},{"attributes":{"OBJECTID":25328,"fac_no":"A4005706","fac_name":"暐迪企業社","fac_addr":"(116)台北市文山區忠順街一段一五一號","utmX":306640,"utmY":2764181,"type":"事業機構"},"geometry":{"x":121.56104940080874,"y":24.984528078610449}},{"attributes":{"OBJECTID":25329,"fac_no":"H4314578","fac_name":"上博資訊實業股份有限公司中壢廠","fac_addr":"(320)桃園市中壢區文化里松柏路九號二樓","utmX":274894,"utmY":2764183,"type":"事業機構"},"geometry":{"x":121.24659214095281,"y":24.985399366331613}},{"attributes":{"OBJECTID":25330,"fac_no":"H42B0297","fac_name":"萬代福營造有限公司","fac_addr":"(248)新北市五股區成泰路一段二號八樓","utmX":279481,"utmY":2764183,"type":"事業機構"},"geometry":{"x":121.29202909223189,"y":24.985317146039996}},{"attributes":{"OBJECTID":25331,"fac_no":"H4302434","fac_name":"德祥工業股份有限公司","fac_addr":"(320)桃園市中壢區文化里松柏路一二號","utmX":274918,"utmY":2764184,"type":"事業機構"},"geometry":{"x":121.24682989369657,"y":24.98540800055601}},{"attributes":{"OBJECTID":25332,"fac_no":"H48A2226","fac_name":"達方電子股份有限公司精機廠","fac_addr":"(333)桃園市龜山區山頂里山鶯路一六七號","utmX":283127,"utmY":2764185,"type":"事業機構"},"geometry":{"x":121.3281447758802,"y":24.985259954519609}},{"attributes":{"OBJECTID":25333,"fac_no":"F05A4780","fac_name":"安心食品服務股份有限公司大坪林分公司","fac_addr":"(231)新北市新店區民權路四五號一、二樓","utmX":303687,"utmY":2764185,"type":"事業機構"},"geometry":{"x":121.53179953756754,"y":24.984671582871304}},{"attributes":{"OBJECTID":25334,"fac_no":"H5201098","fac_name":"傑克電機股份有限公司","fac_addr":"(327)桃園市新屋區清華里北勢二\u25CB之一二號","utmX":260180,"utmY":2764186,"type":"事業機構"},"geometry":{"x":121.10084020966853,"y":24.985596577569321}},{"attributes":{"OBJECTID":25335,"fac_no":"H48A8858","fac_name":"利晉工程股份有限公司","fac_addr":"(330)桃園市桃園區中平路一\u25CB二號一一樓之一","utmX":283021,"utmY":2764188,"type":"事業機構"},"geometry":{"x":121.32709486116708,"y":24.985289350653087}},{"attributes":{"OBJECTID":25336,"fac_no":"H48B0316","fac_name":"台達電子工業股份有限公司桃園五廠","fac_addr":"(333)桃園市龜山區山頂里興邦路三一之一號","utmX":283021,"utmY":2764188,"type":"事業機構"},"geometry":{"x":121.32709486116708,"y":24.985289350653087}},{"attributes":{"OBJECTID":25337,"fac_no":"F04A0248","fac_name":"玫瑰彩色沖印店","fac_addr":"(235)新北市中和區忠孝街二號之八","utmX":300571,"utmY":2764188,"type":"事業機構"},"geometry":{"x":121.50093489655774,"y":24.984805754434394}},{"attributes":{"OBJECTID":25338,"fac_no":"F1311453","fac_name":"儒鴻企業股份有限公司中央廠","fac_addr":"台北市中山區長安東路2段80號10樓之3","utmX":293980,"utmY":2764190,"type":"事業機構"},"geometry":{"x":121.43564890699142,"y":24.985029236169467}},{"attributes":{"OBJECTID":25339,"fac_no":"F05B5191","fac_name":"康鼎國際餐飲有限公司-十里安 (中正店)","fac_addr":"NULL","utmX":303886,"utmY":2764192,"type":"事業機構"},"geometry":{"x":121.53377094854002,"y":24.984727722477214}},{"attributes":{"OBJECTID":25340,"fac_no":"F05B3937","fac_name":"京采餐飲企業有限公司","fac_addr":"(231)新北市新店區北新路三段二\u25CB七之一號一樓","utmX":304517,"utmY":2764193,"type":"事業機構"},"geometry":{"x":121.54002117798288,"y":24.984714202827323}},{"attributes":{"OBJECTID":25341,"fac_no":"F13A6027","fac_name":"鬍鬚張股份有限公司土城裕民分公司","fac_addr":"NULL","utmX":295755,"utmY":2764197,"type":"事業機構"},"geometry":{"x":121.45323117823177,"y":24.985039928101852}},{"attributes":{"OBJECTID":25342,"fac_no":"H4210253","fac_name":"台灣科萊恩化學股份有限公司桃園化工廠","fac_addr":"(330)桃園市桃園區大林里興邦路三\u25CB號","utmX":282525,"utmY":2764199,"type":"事業機構"},"geometry":{"x":121.32218197339726,"y":24.985399378560754}},{"attributes":{"OBJECTID":25343,"fac_no":"H4304929","fac_name":"金像電子股份有限公司中壢廠","fac_addr":"(320)桃園市中壢區永福里西園路一一三號及一一三之一號","utmX":273862,"utmY":2764200,"type":"事業機構"},"geometry":{"x":121.23636983678811,"y":24.985569434535741}},{"attributes":{"OBJECTID":25344,"fac_no":"H4308445","fac_name":"技勤企業有限公司","fac_addr":"(320)桃園市中壢區內定里文中路二段二五七巷一三一號","utmX":275568,"utmY":2764201,"type":"事業機構"},"geometry":{"x":121.25326885529289,"y":24.985550664114527}},{"attributes":{"OBJECTID":25345,"fac_no":"F01B4925","fac_name":"建宏揚營造有限公司","fac_addr":"(237)新北市三峽區大德路二三八號","utmX":293404,"utmY":2764202,"type":"事業機構"},"geometry":{"x":121.42994377756392,"y":24.985154165770624}},{"attributes":{"OBJECTID":25346,"fac_no":"F0508612","fac_name":"研華股份有限公司新店廠","fac_addr":"(231)新北市新店區民權路一三\u25CB巷五、七、九號三樓","utmX":303176,"utmY":2764202,"type":"事業機構"},"geometry":{"x":121.52673862228463,"y":24.984843059422186}},{"attributes":{"OBJECTID":25347,"fac_no":"H4218991","fac_name":"台灣麥當勞餐廳股份有限公司桃園愛買中心","fac_addr":"(100)台北市中正區林森南路一號三樓","utmX":279215,"utmY":2764205,"type":"事業機構"},"geometry":{"x":121.28939467525075,"y":24.985520915135449}},{"attributes":{"OBJECTID":25348,"fac_no":"H4800613","fac_name":"友偉工業股份有限公司","fac_addr":"(333)桃園市龜山區福源里湖山街一八\u25CB巷二九號","utmX":284210,"utmY":2764210,"type":"事業機構"},"geometry":{"x":121.33887307793032,"y":24.985461620831437}},{"attributes":{"OBJECTID":25349,"fac_no":"F0719259","fac_name":"順探實業股份有限公司","fac_addr":"(238)新北市樹林區鎮前街二六九巷一二號","utmX":292353,"utmY":2764210,"type":"事業機構"},"geometry":{"x":121.41953343288023,"y":24.985256101923252}},{"attributes":{"OBJECTID":25350,"fac_no":"H5204795","fac_name":"銅鼎企業有限公司","fac_addr":"(327)桃園市新屋區永安里一二鄰下庄子二三六之八號","utmX":253123,"utmY":2764214,"type":"事業機構"},"geometry":{"x":121.03093563781573,"y":24.985880320415784}},{"attributes":{"OBJECTID":25351,"fac_no":"H52A3674","fac_name":"威臺營造有限公司","fac_addr":"(330)桃園市桃園區中寧里同德五街二三三號二樓","utmX":253213,"utmY":2764214,"type":"事業機構"},"geometry":{"x":121.03182715464872,"y":24.98588013243149}},{"attributes":{"OBJECTID":25352,"fac_no":"H43A2716","fac_name":"正謙股份有限公司中壢合江廠","fac_addr":"(320)桃園市中壢區文化里合江二路七號","utmX":274658,"utmY":2764214,"type":"事業機構"},"geometry":{"x":121.24425496889198,"y":24.985683099194638}},{"attributes":{"OBJECTID":25353,"fac_no":"H5200537","fac_name":"神東艾仕得塗料系統股份有限公司","fac_addr":"(327)桃園市新屋區永安里永福路七五六號","utmX":253099,"utmY":2764216,"type":"事業機構"},"geometry":{"x":121.03069790447564,"y":24.985898426440052}},{"attributes":{"OBJECTID":25354,"fac_no":"H43A9455","fac_name":"珈榮企業有限公司","fac_addr":"(320)桃園市中壢區復興里北園二路一號一樓","utmX":274682,"utmY":2764216,"type":"事業機構"},"geometry":{"x":121.24449273990697,"y":24.98570076546698}},{"attributes":{"OBJECTID":25355,"fac_no":"H4301339","fac_name":"震雄機械廠股份有限公司中壢廠","fac_addr":"(320)桃園市中壢區中壢工業區松江北路一號","utmX":275080,"utmY":2764216,"type":"事業機構"},"geometry":{"x":121.24843518358254,"y":24.985694236581743}},{"attributes":{"OBJECTID":25356,"fac_no":"H4203212","fac_name":"鴻冠科技股份有限公司","fac_addr":"(330)桃園市桃園區泰山里玉山街二一四號","utmX":279541,"utmY":2764217,"type":"事業機構"},"geometry":{"x":121.29262415293985,"y":24.985622940242862}},{"attributes":{"OBJECTID":25357,"fac_no":"H53A3916","fac_name":"精工碳素股份有限公司","fac_addr":"(328)桃園市觀音區崙坪里崙坪一之五\u25CB號","utmX":266166,"utmY":2764221,"type":"事業機構"},"geometry":{"x":121.16013609833456,"y":24.98586058167729}},{"attributes":{"OBJECTID":25358,"fac_no":"F04B4019","fac_name":"遠雄營造股份有限公司","fac_addr":"(110)台北市信義區松高路一號二二樓","utmX":301197,"utmY":2764223,"type":"事業機構"},"geometry":{"x":121.5071368930415,"y":24.985100736051066}},{"attributes":{"OBJECTID":25359,"fac_no":"H52A0541","fac_name":"明薘企業有限公司","fac_addr":"(327)桃園市新屋區永安里下庄子二三六之一\u25CB號","utmX":253158,"utmY":2764225,"type":"事業機構"},"geometry":{"x":121.03128236393646,"y":24.985979560328129}},{"attributes":{"OBJECTID":25360,"fac_no":"F0701980","fac_name":"鋒貿企業股份有限公司","fac_addr":"(238)新北市樹林區樹中街三二巷一\u25CB號","utmX":292494,"utmY":2764225,"type":"事業機構"},"geometry":{"x":121.42093055905777,"y":24.985387580587517}},{"attributes":{"OBJECTID":25361,"fac_no":"F04B3912","fac_name":"遠雄營造股份有限公司","fac_addr":"(110)台北市信義區松高路一號二二樓","utmX":301126,"utmY":2764226,"type":"事業機構"},"geometry":{"x":121.50643372822034,"y":24.98513021499986}},{"attributes":{"OBJECTID":25362,"fac_no":"A0195035","fac_name":"台灣電力股份有限公司台北南區營業處","fac_addr":"(220)新北市板橋區四川路一段二八七號","utmX":306191,"utmY":2764228,"type":"事業機構"},"geometry":{"x":121.55660389284857,"y":24.98496909275681}},{"attributes":{"OBJECTID":25363,"fac_no":"H43A7083","fac_name":"芽莊科技股份有限公司","fac_addr":"(320)桃園市中壢區文化里北園路三七之一號","utmX":274468,"utmY":2764232,"type":"事業機構"},"geometry":{"x":121.24237321613514,"y":24.985848685901388}},{"attributes":{"OBJECTID":25364,"fac_no":"H52A1559","fac_name":"弘益光電科技股份有限公司","fac_addr":"(327)桃園市新屋區永安里下庄子二三一之二號","utmX":252881,"utmY":2764233,"type":"事業機構"},"geometry":{"x":121.02853848766365,"y":24.9860523389723}},{"attributes":{"OBJECTID":25365,"fac_no":"H4303440","fac_name":"祐昌染整股份有限公司","fac_addr":"(320)桃園市中壢區北園二路五號","utmX":274588,"utmY":2764234,"type":"事業機構"},"geometry":{"x":121.24356192994887,"y":24.985864801943897}},{"attributes":{"OBJECTID":25366,"fac_no":"F04B3348","fac_name":"東源營造工程股份有限公司","fac_addr":"(110)台北市信義區松高路一號二二樓","utmX":301134,"utmY":2764235,"type":"事業機構"},"geometry":{"x":121.50651330346896,"y":24.985211197744782}},{"attributes":{"OBJECTID":25367,"fac_no":"H48B0405","fac_name":"三石營造有限公司","fac_addr":"(337)桃園市大園區田心里中正西路四五之一號","utmX":282447,"utmY":2764236,"type":"事業機構"},"geometry":{"x":121.32141020903171,"y":24.985735094685619}},{"attributes":{"OBJECTID":25368,"fac_no":"H5200466","fac_name":"太平洋自行車股份有限公司","fac_addr":"(327)桃園市新屋區永安里下庄子二三六號","utmX":253018,"utmY":2764238,"type":"事業機構"},"geometry":{"x":121.02989558722936,"y":24.986097214544522}},{"attributes":{"OBJECTID":25369,"fac_no":"F05A8950","fac_name":"潤昶有限公司","fac_addr":"(236)新北市土城區青雲路五二一巷五號一樓","utmX":303457,"utmY":2764240,"type":"事業機構"},"geometry":{"x":121.52952346348241,"y":24.985176246796868}},{"attributes":{"OBJECTID":25370,"fac_no":"H4204497","fac_name":"三洋紡織纖維股份有限公司","fac_addr":"(330)桃園市桃園區大林里建國東路二四號","utmX":282418,"utmY":2764241,"type":"事業機構"},"geometry":{"x":121.32112306457816,"y":24.985780856079128}},{"attributes":{"OBJECTID":25371,"fac_no":"H4809901","fac_name":"台達電子工業股份有限公司桃園二廠","fac_addr":"(333)桃園市龜山區山頂里山鶯路二五二號一樓及三至一\u25CB樓","utmX":283030,"utmY":2764243,"type":"事業機構"},"geometry":{"x":121.32718532508167,"y":24.985785708573037}},{"attributes":{"OBJECTID":25372,"fac_no":"H48A3383","fac_name":"達爾生技股份有限公司","fac_addr":"(333)桃園市龜山區山頂里山鶯路二五二號三及七樓","utmX":283030,"utmY":2764243,"type":"事業機構"},"geometry":{"x":121.32718532508167,"y":24.985785708573037}},{"attributes":{"OBJECTID":25373,"fac_no":"F13A4843","fac_name":"中華電信股份有限公司台灣北區電信分公司新北營運處","fac_addr":"(234)新北市永和區國光路八號","utmX":296324,"utmY":2764243,"type":"事業機構"},"geometry":{"x":121.45886886994127,"y":24.985437950347599}},{"attributes":{"OBJECTID":25374,"fac_no":"F13A3370","fac_name":"禪心營造有限公司","fac_addr":"(234)新北市永和區中和路三八一號一二樓","utmX":296325,"utmY":2764243,"type":"事業機構"},"geometry":{"x":121.45887877533077,"y":24.985437919806238}},{"attributes":{"OBJECTID":25375,"fac_no":"H4810600","fac_name":"台灣華歌爾股份有限公司一廠","fac_addr":"(330)桃園市龜山區山頂里興邦路二九之一號","utmX":281942,"utmY":2764244,"type":"事業機構"},"geometry":{"x":121.31640807661657,"y":24.985818039934344}},{"attributes":{"OBJECTID":25376,"fac_no":"F1313279","fac_name":"台灣麥當勞餐廳股份有限公司土城裕民分公司","fac_addr":"(236)新北市土城區裕民路一八\u25CB號一、二樓及一八二號一、二樓","utmX":295556,"utmY":2764244,"type":"事業機構"},"geometry":{"x":121.45126155898238,"y":24.985470239563025}},{"attributes":{"OBJECTID":25377,"fac_no":"F04B4247","fac_name":"久和營造工程股份有限公司","fac_addr":"(106)台北市大安區和平東路一段五九號二樓","utmX":301211,"utmY":2764244,"type":"事業機構"},"geometry":{"x":121.50727634503231,"y":24.98528985239242}},{"attributes":{"OBJECTID":25378,"fac_no":"H48A6793","fac_name":"乾坤科技股份有限公司","fac_addr":"(308)新竹縣寶山鄉研發二路二號","utmX":283004,"utmY":2764247,"type":"事業機構"},"geometry":{"x":121.32692787564423,"y":24.985822387559718}},{"attributes":{"OBJECTID":25379,"fac_no":"H4810833","fac_name":"達創科技股份有限公司","fac_addr":"(333)桃園市龜山區山頂里山鶯路二五二號二樓","utmX":283005,"utmY":2764247,"type":"事業機構"},"geometry":{"x":121.32693778122167,"y":24.98582236579956}},{"attributes":{"OBJECTID":25380,"fac_no":"F05B2810","fac_name":"台灣松下營造股份有限公司","fac_addr":"(241)新北市三重區重新路四段三九號四樓之七","utmX":303495,"utmY":2764251,"type":"事業機構"},"geometry":{"x":121.52990028910027,"y":24.985274215222255}},{"attributes":{"OBJECTID":25381,"fac_no":"H43C0893","fac_name":"華阜營造股份有限公司","fac_addr":"(334)桃園市八德區大仁里桃鶯路宏福巷一弄二衖一五之三號","utmX":269280,"utmY":2764252,"type":"事業機構"},"geometry":{"x":121.19098286261389,"y":24.986104073368903}},{"attributes":{"OBJECTID":25382,"fac_no":"H4304223","fac_name":"台灣氣動工業股份有限公司桃園廠","fac_addr":"(320)桃園市中壢區松江南路一三號","utmX":274152,"utmY":2764253,"type":"事業機構"},"geometry":{"x":121.23924339640777,"y":24.986043345447712}},{"attributes":{"OBJECTID":25383,"fac_no":"H4215623","fac_name":"德仁醫院","fac_addr":"(330)桃園市桃園區桃鶯路二四五號","utmX":281336,"utmY":2764253,"type":"事業機構"},"geometry":{"x":121.31040549264156,"y":24.985911935429016}},{"attributes":{"OBJECTID":25384,"fac_no":"F0511879","fac_name":"北爾電子股份有限公司","fac_addr":"(231)新北市新店區中正路五\u25CB一之一四、之一五號四樓","utmX":303025,"utmY":2764253,"type":"事業機構"},"geometry":{"x":121.52524488686625,"y":24.985308774573831}},{"attributes":{"OBJECTID":25385,"fac_no":"H49A6619","fac_name":"良記營造股份有限公司","fac_addr":"(328)桃園市觀音區大潭里大潭一八之一\u25CB號一樓","utmX":278536,"utmY":2764258,"type":"事業機構"},"geometry":{"x":121.28266987245335,"y":24.986012341054387}},{"attributes":{"OBJECTID":25386,"fac_no":"H4889105","fac_name":"華視攝影社","fac_addr":"桃園市龜山區山鶯路103號1樓","utmX":283038,"utmY":2764258,"type":"事業機構"},"geometry":{"x":121.32726492816023,"y":24.985920958115418}},{"attributes":{"OBJECTID":25387,"fac_no":"F0507473","fac_name":"倡新科技股份有限公司","fac_addr":"新北市新店區中正路５２５號４樓","utmX":303826,"utmY":2764258,"type":"事業機構"},"geometry":{"x":121.53317920497285,"y":24.985325701344941}},{"attributes":{"OBJECTID":25388,"fac_no":"F0510729","fac_name":"倍力科技股份有限公司新店廠","fac_addr":"新北市新店區民權路108之1號3樓","utmX":303328,"utmY":2764259,"type":"事業機構"},"geometry":{"x":121.52824641735323,"y":24.985352319963845}},{"attributes":{"OBJECTID":25389,"fac_no":"H52A4107","fac_name":"冠蓁營造股份有限公司","fac_addr":"(334)桃園市八德區永豐路四二二號一樓","utmX":257207,"utmY":2764261,"type":"事業機構"},"geometry":{"x":121.07139092268645,"y":24.986290747344832}},{"attributes":{"OBJECTID":25390,"fac_no":"H42B2362","fac_name":"育誠土木包工業","fac_addr":"(337)桃園市大園區田心里仁德路一三二號一樓","utmX":281767,"utmY":2764261,"type":"事業機構"},"geometry":{"x":121.31467498931033,"y":24.985975195749972}},{"attributes":{"OBJECTID":25391,"fac_no":"H43A1986","fac_name":"欣新開發有限公司中壢廠","fac_addr":"(320)桃園市中壢區北園路三六號四樓","utmX":274491,"utmY":2764262,"type":"事業機構"},"geometry":{"x":121.24260157763477,"y":24.986119164242332}},{"attributes":{"OBJECTID":25392,"fac_no":"F05A8772","fac_name":"弘訊科技股份有限公司二廠","fac_addr":"(231)新北市新店區中正路五二九之一號九樓","utmX":303817,"utmY":2764265,"type":"事業機構"},"geometry":{"x":121.53309033005215,"y":24.985389216753418}},{"attributes":{"OBJECTID":25393,"fac_no":"H4882295","fac_name":"邑昇實業股份有限公司龜山廠","fac_addr":"(333)桃園市龜山區山頂里山鶯路中華巷二號一、二、三樓","utmX":283378,"utmY":2764267,"type":"事業機構"},"geometry":{"x":121.33063304370197,"y":24.98599476825083}},{"attributes":{"OBJECTID":25394,"fac_no":"H4800793","fac_name":"慶義工業股份有限公司","fac_addr":"(333)桃園市龜山區兔坑里湖山街二一一巷八弄二號","utmX":284411,"utmY":2764268,"type":"事業機構"},"geometry":{"x":121.34086553425949,"y":24.985980711938332}},{"attributes":{"OBJECTID":25395,"fac_no":"F0507160","fac_name":"弘訊科技股份有限公司","fac_addr":"(231)新北市新店區中正路五二九號九樓","utmX":303817,"utmY":2764270,"type":"事業機構"},"geometry":{"x":121.53309052469507,"y":24.985434356792691}},{"attributes":{"OBJECTID":25396,"fac_no":"H43B4066","fac_name":"友嘉綠能科技股份有限公司","fac_addr":"(320)桃園市中壢區復興里北園二路三號","utmX":274610,"utmY":2764271,"type":"事業機構"},"geometry":{"x":121.24378051300731,"y":24.986198492888381}},{"attributes":{"OBJECTID":25397,"fac_no":"F1309793","fac_name":"家福股份有限公司土城分公司","fac_addr":"新北市土城區青雲路一五二號B一","utmX":295557,"utmY":2764275,"type":"事業機構"},"geometry":{"x":121.45127248596742,"y":24.985750081212743}},{"attributes":{"OBJECTID":25398,"fac_no":"H4801647","fac_name":"中誠企業股份有限公司","fac_addr":"(333)桃園市龜山區山頂里中興路二號","utmX":283226,"utmY":2764276,"type":"事業機構"},"geometry":{"x":121.3291276105724,"y":24.986079359885132}},{"attributes":{"OBJECTID":25399,"fac_no":"F0502987","fac_name":"威盛電子股份有限公司","fac_addr":"(231)新北市新店區中正路五三五號二及三及八及一\u25CB樓、五三三號三及四及八及一\u25CB樓、五二七號三及七及八及一\u25CB樓、五二五號二及三及七及八及九及一\u25CB樓、五二五之一號二及三及七及八及一\u25CB樓、五二九之一號七及八及一\u25CB樓、五二九號七及八樓","utmX":303848,"utmY":2764276,"type":"事業機構"},"geometry":{"x":121.53339782199983,"y":24.985487424612728}},{"attributes":{"OBJECTID":25400,"fac_no":"H48B0554","fac_name":"穩懋半導體股份有限公司龜山廠","fac_addr":"(333)桃園市龜山區文化里科技七路六九號","utmX":282897,"utmY":2764277,"type":"事業機構"},"geometry":{"x":121.32586869270401,"y":24.986095559679409}}]}